[{"file":"c:/SALESFORCE/related-contacts-lwc-salesforce/force-app/main/default/lwc/relatedRelationshipContactsList/relatedRelationshipContactsList.js","metadata":{"decorators":[{"type":"api","targets":[{"name":"recordId","type":"property","value":{"type":"unresolved"}}]},{"type":"wire","targets":[{"type":"method","name":"wiredContacts","static":{},"params":{"contactId":"recordId"},"adapter":{"name":"getRelatedContacts","reference":"@salesforce/apex/RelatedContactsController.getRelatedContacts"}}]}],"classMembers":[{"name":"recordId","type":"property","value":{"type":"unresolved"},"decorator":"api","loc":{"start":{"line":5,"column":4},"end":{"line":5,"column":18}}},{"name":"relatedContacts","type":"property","loc":{"start":{"line":6,"column":4},"end":{"line":6,"column":25}}},{"name":"error","type":"property","loc":{"start":{"line":7,"column":4},"end":{"line":7,"column":10}}},{"name":"wiredContacts","type":"method","decorator":"wire","loc":{"start":{"line":9,"column":4},"end":{"line":18,"column":5}}},{"name":"hasContacts","type":"property","loc":{"start":{"line":20,"column":4},"end":{"line":22,"column":5}}}],"declarationLoc":{"start":{"line":4,"column":0},"end":{"line":23,"column":1}},"doc":"","exports":[{"type":"ExportDefaultDeclaration"}]},"updatedAt":"2025-05-29T07:10:01.928Z","_allAttributes":null,"_properties":null,"_methods":null}]